{"date":"2026-12-04","difficulty":"hard","size":6,"grid":["RIALTO","E#K#R#","PHARAH","L#N#N#","A#D#C#","Y#E#E#"],"entries":[{"number":1,"row":0,"col":0,"dir":"across","answer":"RIALTO","clue":"Map born from the Retribution mission"},{"number":4,"row":2,"col":0,"dir":"across","answer":"PHARAH","clue":"Fareeha Amari's call sign"},{"number":1,"row":0,"col":0,"dir":"down","answer":"REPLAY","clue":"System for rewatching your own games"},{"number":2,"row":0,"col":2,"dir":"down","answer":"AKANDE","clue":"Ogundimu who leads Talon's council"},{"number":3,"row":0,"col":4,"dir":"down","answer":"TRANCE","clue":"Zenyatta's giant heal ultimate, abbreviated by casters"}]}
