{"date":"2027-02-26","difficulty":"hard","size":5,"grid":["STORM","O###E","NEPAL","I###E","CHOKE"],"entries":[{"number":1,"row":0,"col":0,"dir":"across","answer":"STORM","clue":"Hanzo's ___ Arrows"},{"number":3,"row":2,"col":0,"dir":"across","answer":"NEPAL","clue":"Where the Shambali preach omnic enlightenment"},{"number":4,"row":4,"col":0,"dir":"across","answer":"CHOKE","clue":"Narrow path every team fight funnels through"},{"number":1,"row":0,"col":0,"dir":"down","answer":"SONIC","clue":"Hanzo's wallhack arrow, or Lucio's gun"},{"number":2,"row":0,"col":4,"dir":"down","answer":"MELEE","clue":"Quick punch on the V key, by default"}]}
