{"date":"2027-06-05","difficulty":"hard","size":7,"grid":["RANKERS","#T####H","FLORIDA","#A####T","ONESHOT","#T####E","PARKOUR"],"entries":[{"number":1,"row":0,"col":0,"dir":"across","answer":"RANKERS","clue":"They won the OWCS 2026 Pacific Stage 1 Open Qualifier, pre-acquisition"},{"number":4,"row":2,"col":0,"dir":"across","answer":"FLORIDA","clue":"Mayhem's home state"},{"number":5,"row":4,"col":0,"dir":"across","answer":"ONESHOT","clue":"Kill from full health in a single combo"},{"number":6,"row":6,"col":0,"dir":"across","answer":"PARKOUR","clue":"Mercy-only custom game genre"},{"number":2,"row":0,"col":1,"dir":"down","answer":"ATLANTA","clue":"Its Reign was swept in the 2021 Grand Finals"},{"number":3,"row":0,"col":6,"dir":"down","answer":"SHATTER","clue":"Slam that floors everyone in front of the hammer"}]}
