{"date":"2027-02-12","difficulty":"hard","size":5,"grid":["DROPS","#O##E","LUCIO","#T##U","NEPAL"],"entries":[{"number":1,"row":0,"col":0,"dir":"across","answer":"DROPS","clue":"Twitch rewards for watching OWCS"},{"number":4,"row":2,"col":0,"dir":"across","answer":"LUCIO","clue":"His drop is a Sound Barrier"},{"number":5,"row":4,"col":0,"dir":"across","answer":"NEPAL","clue":"Where the Shambali preach omnic enlightenment"},{"number":2,"row":0,"col":1,"dir":"down","answer":"ROUTE","clue":"Escort map through a Deadlock Gorge diner"},{"number":3,"row":0,"col":4,"dir":"down","answer":"SEOUL","clue":"Dynasty's OWL city"}]}
