{
  "Ana": "/heroes/ana.webp",
  "Echo": "/heroes/echo.webp",
  "Emre": "/heroes/emre.webp",
  "Genji": "/heroes/genji.webp",
  "Hazard": "/heroes/hazard.webp",
  "Illari": "/heroes/illari.webp",
  "Jetpack Cat": "/heroes/jetpack-cat.webp",
  "Kiriko": "/heroes/kiriko.webp",
  "Lucio": "/heroes/lucio.webp",
  "Mizuki": "/heroes/mizuki.webp",
  "Pharah": "/heroes/pharah.webp",
  "Reaper": "/heroes/reaper.webp",
  "Reinhardt": "/heroes/reinhardt.webp",
  "Roadhog": "/heroes/roadhog.webp",
  "Sigma": "/heroes/sigma.webp",
  "Wrecking Ball": "/heroes/wrecking-ball.webp",
  "Zarya": "/heroes/zarya.webp",
  "Zenyatta": "/heroes/zenyatta.webp"
}
